django_dart_reverse/__init__.py
django_dart_reverse/admin.py
django_dart_reverse/apps.py
django_dart_reverse/models.py
django_dart_reverse/tests.py
django_dart_reverse/views.py
django_dart_reverse/management/__init__.py
django_dart_reverse/management/commands/__init__.py
django_dart_reverse/management/commands/collectstatic_dart_reverse.py
django_dart_reverse/migrations/__init__.py
django_dart_reverse/templates/__init__.py
django_dart_reverse/templates/dart/__init__.py
django_dart_reverse/templates/dart/dart_file.tpl
django_dart_reverse/utils/__init__.py
django_dart_reverse/utils/collect_urls.py
django_dart_reverse/utils/reverse_class.py
django_dart_reverse-0.0.14.dist-info/LICENSE
django_dart_reverse-0.0.14.dist-info/METADATA
django_dart_reverse-0.0.14.dist-info/WHEEL
django_dart_reverse-0.0.14.dist-info/top_level.txt
django_dart_reverse-0.0.14.dist-info/RECORD
